chat_provider.py
chat/__init__.py
chat/chat.py
chat/error_utils.py
chat/exceptions.py
chat/format.py
chat/logging_setup.py
chat/mcp_client.py
chat/providers/__init__.py
chat/providers/anthropic_provider.py
chat/providers/base.py
chat/providers/openai_provider.py
tests/__init__.py
tests/test_chat_provider.py
tests/test_chatbot.py
chat_in_a_nutshell-1.6.0.dist-info/LICENSE
chat_in_a_nutshell-1.6.0.dist-info/METADATA
chat_in_a_nutshell-1.6.0.dist-info/WHEEL
chat_in_a_nutshell-1.6.0.dist-info/entry_points.txt
chat_in_a_nutshell-1.6.0.dist-info/top_level.txt
chat_in_a_nutshell-1.6.0.dist-info/RECORD
