Metadata-Version: 2.1
Name: chat-in-a-nutshell
Version: 1.6.0
Summary: A terminal-based script for interacting with OpenAI's and Anthropic's API.
Home-page: https://github.com/thedavidnovak/chat-in-a-nutshell
Author: David Novák
Classifier: Programming Language :: Python :: 3
Classifier: License :: OSI Approved :: MIT License
Classifier: Operating System :: OS Independent
Requires-Python: >=3.11
License-File: LICENSE
Requires-Dist: httpx~=0.28.1
Requires-Dist: openai~=1.62.0
Requires-Dist: anthropic~=0.49.0
Requires-Dist: mcp~=1.9.0
Requires-Dist: aiofiles~=24.1.0
Provides-Extra: dev
Requires-Dist: pytest>=7.0.0; extra == "dev"
Requires-Dist: pytest-asyncio>=0.21.0; extra == "dev"
Requires-Dist: pytest-mock>=3.10.0; extra == "dev"
Requires-Dist: flake8>=5.0.0; extra == "dev"
Requires-Dist: flake8-quotes>=3.3.0; extra == "dev"
Requires-Dist: autopep8>=2.0.0; extra == "dev"
Requires-Dist: black>=23.0.0; extra == "dev"
